ratelimits/__init__.py
ratelimits/decorators.py
ratelimits/utilities.py
ratelimits-0.1.5.dist-info/licenses/LICENSE
ratelimits-0.1.5.dist-info/METADATA
ratelimits-0.1.5.dist-info/WHEEL
ratelimits-0.1.5.dist-info/top_level.txt
ratelimits-0.1.5.dist-info/RECORD
