Metadata-Version: 2.4
Name: ratelimits
Version: 0.1.5
Summary: A simple function decorator that enables rate limiting using fixed window or sliding window strategies.
Author-email: Juan Carlos Largo <juanca.buy@gmail.com>
License: MIT License
Project-URL: Homepage, https://github.com/Juancaa/ratelimits
Project-URL: Issues, https://github.com/Juancaa/ratelimits/issues
Requires-Python: >=3.8
License-File: LICENSE
Dynamic: license-file
